tox_pipenv/__init__.py
tox_pipenv/plugin.py
tox_pipenv-1.10.1.dist-info/LICENSE
tox_pipenv-1.10.1.dist-info/METADATA
tox_pipenv-1.10.1.dist-info/WHEEL
tox_pipenv-1.10.1.dist-info/entry_points.txt
tox_pipenv-1.10.1.dist-info/top_level.txt
tox_pipenv-1.10.1.dist-info/RECORD
