Metadata-Version: 2.1
Name: tox-pipenv
Version: 1.10.1
Summary: A pipenv plugin for tox
Home-page: https://github.com/tox-dev/tox-pipenv
Author: Anthony Shaw
License: MIT
Platform: unix
Platform: linux
Platform: osx
Platform: cygwin
Platform: win32
Classifier: Development Status :: 4 - Beta
Classifier: Intended Audience :: Developers
Classifier: License :: OSI Approved :: MIT License
Classifier: Operating System :: POSIX
Classifier: Operating System :: Microsoft :: Windows
Classifier: Operating System :: MacOS :: MacOS X
Classifier: Topic :: Software Development :: Testing
Classifier: Topic :: Software Development :: Libraries
Classifier: Topic :: Utilities
Classifier: Programming Language :: Python
Requires-Dist: tox (>=3.0.0)
Requires-Dist: pipenv (>=2018.05.18)
